codestripper/__init__.py
codestripper/__main__.py
codestripper/cli.py
codestripper/code_stripper.py
codestripper/errors.py
codestripper/py.typed
codestripper/tags/__init__.py
codestripper/tags/add.py
codestripper/tags/errors.py
codestripper/tags/ignore_file.py
codestripper/tags/legacy.py
codestripper/tags/remove.py
codestripper/tags/replace.py
codestripper/tags/tag.py
codestripper/tags/uncomment.py
codestripper/tokenizer.py
codestripper/utils/__init__.py
codestripper/utils/comments.py
codestripper/utils/enums.py
codestripper/utils/file.py
codestripper/utils/logger.py
codestripper-1.1.1.dist-info/LICENSE
codestripper-1.1.1.dist-info/METADATA
codestripper-1.1.1.dist-info/WHEEL
codestripper-1.1.1.dist-info/entry_points.txt
codestripper-1.1.1.dist-info/RECORD
