Metadata-Version: 2.3
Name: codestripper
Version: 1.1.1
Summary: CodeStripper used to strip code from assignments
License: MIT
Author: Bonajo
Author-email: m.bonajo@fontys.nl
Maintainer: Bonajo
Maintainer-email: m.bonajo@fontys.nl
Requires-Python: >=3.8,<4.0
Classifier: License :: OSI Approved :: MIT License
Classifier: Programming Language :: Python :: 3
Classifier: Programming Language :: Python :: 3.8
Classifier: Programming Language :: Python :: 3.9
Classifier: Programming Language :: Python :: 3.10
Classifier: Programming Language :: Python :: 3.11
Classifier: Programming Language :: Python :: 3.12
Classifier: Programming Language :: Python :: 3.13
Project-URL: Homepage, https://github.com/FontysVenlo/codestripper
Project-URL: Repository, https://github.com/FontysVenlo/codestripper
